lektor_datetime_helpers.py
lektor_datetime_helpers-1.0.1.dist-info/LICENSE
lektor_datetime_helpers-1.0.1.dist-info/METADATA
lektor_datetime_helpers-1.0.1.dist-info/WHEEL
lektor_datetime_helpers-1.0.1.dist-info/entry_points.txt
lektor_datetime_helpers-1.0.1.dist-info/top_level.txt
lektor_datetime_helpers-1.0.1.dist-info/RECORD
