Metadata-Version: 2.1
Name: lektor-datetime-helpers
Version: 1.0.1
Summary: Lektor plugin to help with dates and times
Home-page: https://github.com/dairiki/lektor-datetime-helpers
Author: Jeff Dairiki
Author-email: dairiki@dairiki.org
License: BSD
Keywords: lektor,date,datetime
Platform: UNKNOWN
Classifier: Development Status :: 5 - Production/Stable
Classifier: Environment :: Plugins
Classifier: Environment :: Web Environment
Classifier: Framework :: Lektor
Classifier: Intended Audience :: Developers
Classifier: License :: OSI Approved :: BSD License
Classifier: Programming Language :: Python :: 3
Classifier: Programming Language :: Python :: 3.6
Classifier: Programming Language :: Python :: 3.7
Classifier: Programming Language :: Python :: 3.8
Classifier: Programming Language :: Python :: 3.9
Classifier: Programming Language :: Python :: 3.10
Classifier: Topic :: Internet :: WWW/HTTP
Requires-Python: >=3.6
License-File: LICENSE
